{
    "x_ij_mccormick": [
        0.0,
        0.5397776532540399,
        0.0,
        0.0,
        0.43811429830216064,
        0.0,
        1.4848680250435553,
        0.0,
        0.0,
        0.0,
        0.0,
        0.0,
        0.0,
        0.0,
        0.0,
        0.0,
        0.0,
        0.0,
        0.2278151442289198,
        0.0,
        0.0,
        0.0,
        0.0,
        0.0,
        0.0,
        0.0,
        0.0,
        2.0,
        0.0,
        0.0,
        0.0,
        0.0,
        0.0,
        0.0,
        0.0,
        0.0,
        0.0,
        0.0,
        0.0,
        0.0,
        0.0,
        0.0,
        0.0,
        0.8071450704886429,
        0.0,
        0.0,
        0.0,
        0.0,
        0.0,
        0.0,
        0.0,
        0.0,
        0.0,
        0.0,
        0.0,
        0.0,
        0.0,
        0.4040206136356508,
        0.0,
        1.8614545393469815,
        0.0,
        0.0,
        0.0,
        0.0,
        6.0,
        0.0,
        0.0,
        0.0,
        0.0,
        0.7721848557710802,
        0.0,
        0.0,
        0.0,
        0.0,
        0.0,
        0.0,
        0.01111854858976491,
        0.531792845405274,
        0.0,
        0.0,
        0.0,
        0.0,
        0.0,
        0.0,
        0.0,
        0.0,
        0.0,
        0.0,
        0.0,
        0.0,
        0.0,
        0.0,
        0.0,
        0.0,
        0.0,
        0.0,
        0.0,
        0.6941403648670457,
        0.0,
        0.00791017257951532,
        0.0,
        0.0,
        0.0,
        0.0,
        0.0,
        0.0,
        0.0,
        0.0,
        0.0,
        0.0,
        0.0,
        0.0,
        0.041414875461829204,
        2.9065029901202446,
        0.0,
        0.0
    ],
    "x_il_mccormick": [
        0.0,
        0.0,
        0.0,
        2.272374530147655,
        4.155211980582106,
        0.761579413844902,
        0.0,
        0.0,
        0.0,
        0.655175238223846,
        0.0,
        3.0,
        0.0,
        0.0,
        2.6147560026986567,
        0.0,
        0.0,
        0.0,
        5.323162448082204,
        0.0,
        0.3449630347179533,
        0.7424340125217777,
        3.0,
        1.1050099870564178,
        1.8949900129435822,
        0.0,
        2.676837551917796,
        0.0,
        3.0,
        0.0,
        2.595979386364349,
        0.0,
        0.0,
        0.0,
        0.0,
        0.0,
        0.0,
        0.0,
        1.8650703997156393,
        0.18380073357615295,
        0.0,
        0.0,
        3.0,
        0.0,
        0.0,
        1.7959848232671762,
        0.0,
        3.0,
        0.0,
        0.0,
        0.0,
        0.0,
        0.0,
        0.0,
        4.729980596802342,
        0.0,
        0.0,
        0.0,
        0.0,
        0.0,
        0.0,
        0.0,
        0.0,
        0.0,
        0.13854546065301843,
        0.0,
        0.0,
        3.490253984357761,
        1.5618281500601652,
        0.0,
        7.264797065695388
    ],
    "x_lj_mccormick": [
        1.5618857016978394,
        4.978612464361778,
        0.0,
        0.9080996332119236,
        0.5151319749564446,
        0.9888814514102351,
        0.0,
        0.0,
        2.0,
        0.30585963513295433,
        0.6216901332385464,
        1.5257938799820498,
        0.9585851245381708,
        0.5156209954797795,
        1.46022234674596,
        0.0,
        0.0,
        0.0,
        0.47420612001795015,
        1.0655715332360898,
        0.0,
        2.0,
        0.9009948103235941,
        0.13854546065301843,
        0.0,
        0.0,
        5.595979386364349,
        2.39326352307443,
        0.0,
        0.01075709056122054,
        2.0,
        0.9892429094387795,
        0.01075709056122054,
        2.0,
        6.0,
        0.0,
        2.0,
        1.0,
        0.0,
        0.0,
        1.468207154594726,
        3.60673647692557,
        0.0,
        1.192854929511357,
        4.018418660972472,
        0.5057665401584421,
        2.0,
        0.08399019420856113,
        0.0,
        0.9160098057914389,
        1.3783098667614535,
        3.0827399193185347,
        0.0
    ],
    "q_mccormick": [
        0.0,
        0.0,
        0.0,
        0.757458176715885,
        0.8047714812424793,
        0.2575659874782223,
        0.0,
        0.0,
        0.0,
        0.24254182328411503,
        0.0,
        1.0,
        0.0,
        0.0,
        0.3268445003373321,
        0.0,
        0.0,
        0.26988882662701996,
        0.6653953060102755,
        0.0,
        0.057493839119658885,
        0.7424340125217777,
        1.0,
        0.40133839224427464,
        0.23687375161794777,
        0.0,
        0.3346046939897245,
        0.0,
        0.73011117337298,
        0.9307272696734907,
        0.6891549333807268,
        0.0,
        0.0,
        0.0,
        0.0,
        0.0,
        0.0,
        0.0,
        0.31084506661927325,
        0.09190036678807648,
        0.0,
        0.0,
        1.0,
        0.0,
        0.20840258358297814,
        0.5986616077557254,
        0.0,
        1.0,
        0.0,
        0.0,
        0.0,
        0.0,
        0.0,
        0.0,
        0.734103577297363,
        0.0,
        0.0,
        0.0,
        0.0,
        0.0,
        0.0,
        0.0,
        0.0,
        0.0,
        0.06927273032650921,
        0.0,
        0.0,
        0.43628174804472014,
        0.19522851875752065,
        0.0,
        0.9080996332119236
    ],
    "w_mccormick": [
        1.3783098667614535,
        1.2176695196028955,
        0.0,
        0.0,
        1.8650703997156393,
        0.0,
        0.0,
        0.0,
        0.0,
        0.0,
        0.0,
        0.0,
        0.0,
        0.0,
        0.0,
        0.0,
        2.0,
        0.08399019420856113,
        0.0,
        0.9160098057914389,
        0.0,
        0.0,
        0.0,
        0.0,
        0.0,
        0.0,
        0.0,
        0.0,
        1.192854929511357,
        2.962357051070749,
        0.0,
        0.0,
        0.0,
        0.0,
        0.0,
        0.0,
        0.0,
        0.0,
        0.0,
        0.0,
        0.0,
        1.056061609901723,
        0.5057665401584421,
        0.0,
        0.3449630347179533,
        0.0,
        0.0,
        0.0,
        0.0,
        1.468207154594726,
        3.2617734422076166,
        0.0,
        0.0,
        0.0,
        0.0,
        0.0,
        0.0,
        0.0,
        0.0,
        2.0,
        1.0,
        0.0,
        0.0,
        0.0,
        0.0,
        0.0,
        0.0,
        0.0,
        0.0,
        0.0,
        0.0,
        0.0,
        0.0,
        0.0,
        0.6536890006746642,
        1.9610670020239924,
        0.0,
        0.47374750323589554,
        1.4212425097076866,
        0.0,
        0.0,
        0.0,
        0.0,
        0.0,
        0.0,
        0.0,
        0.0,
        0.0,
        0.0,
        0.0,
        0.0,
        0.0,
        0.8725634960894403,
        2.617690488268321,
        0.0,
        0.0,
        0.0,
        0.0,
        0.0,
        0.0,
        0.0,
        2.0,
        0.9892429094387795,
        0.01075709056122054,
        0.0,
        0.0,
        0.0,
        0.0,
        0.0,
        0.0,
        0.0,
        0.0,
        0.0,
        0.0,
        0.0,
        0.0,
        0.0,
        0.0,
        3.992371836061653,
        1.3200335214593306,
        0.0,
        0.01075709056122054,
        0.0,
        1.6036075503026963,
        1.0732300016150995,
        0.0,
        0.0,
        0.0,
        0.0,
        0.0,
        0.0,
        0.0,
        0.0,
        0.0,
        0.0,
        0.0,
        0.0,
        0.0,
        0.0,
        0.0,
        0.0,
        0.0,
        0.0,
        0.0,
        0.0,
        0.0,
        0.0,
        0.0,
        0.0,
        0.0,
        0.0,
        0.13854546065301843,
        0.0,
        0.8026767844885492,
        0.3023332025678687,
        0.0,
        0.0,
        1.1973232155114508,
        0.5986616077557254,
        0.0,
        0.0,
        0.0,
        0.0,
        0.0,
        0.0,
        0.0,
        0.0,
        0.0,
        0.0,
        0.0,
        0.0,
        0.0,
        0.0,
        1.46022234674596,
        0.0,
        0.0,
        0.0,
        0.47420612001795015,
        1.0655715332360898,
        0.0,
        0.0,
        0.0,
        0.0,
        0.0,
        0.0,
        0.0,
        0.0,
        0.0,
        0.0,
        0.0,
        0.0,
        0.0,
        0.0,
        0.0,
        1.5257938799820498,
        0.9585851245381708,
        0.5156209954797795,
        0.0,
        0.0,
        0.0,
        0.0,
        0.0,
        0.0,
        0.0,
        0.0,
        0.0,
        1.51491635343177,
        0.13576804347733837,
        0.6216901332385464,
        0.48508364656823005,
        0.17009159165561594,
        0.0,
        0.0,
        0.0,
        0.0,
        0.0,
        0.0,
        0.0,
        0.0,
        0.0,
        0.0,
        0.0,
        0.0,
        0.0,
        0.0,
        0.5151319749564446,
        0.24644743888845744,
        0.0,
        0.0,
        0.0,
        0.0,
        0.0,
        0.0,
        0.0,
        0.7424340125217777,
        0.0,
        0.0,
        0.0,
        0.0,
        0.0,
        0.0,
        0.0,
        0.0,
        0.0,
        0.0,
        0.0,
        0.0,
        0.0,
        0.0,
        0.18380073357615295,
        0.0,
        0.0,
        0.0,
        0.0,
        0.0,
        0.0,
        0.0,
        1.3780849681216865,
        4.978612464361778,
        0.0,
        0.9080996332119236
    ]
}