{
    "x_ij_mccormick": [
        0.0,
        0.0,
        0.5494206617262668,
        0.0,
        0.0,
        0.0,
        1.2842562461179887,
        0.0,
        0.0,
        0.0,
        0.0,
        0.0,
        0.0,
        0.0,
        0.0,
        0.0,
        0.0,
        0.0,
        0.331439298794868,
        0.0,
        0.0,
        0.0,
        0.0,
        0.0,
        0.0,
        0.0,
        0.0,
        2.0,
        0.0,
        0.0,
        0.0,
        0.0,
        0.0,
        0.0,
        0.0,
        0.0,
        0.0,
        0.0,
        0.0,
        0.0,
        0.0,
        0.0,
        0.0,
        0.29881190550975045,
        0.4849246559264566,
        0.0,
        0.0,
        0.0,
        0.0,
        0.0,
        0.0,
        0.0,
        0.0,
        0.0,
        0.0,
        0.19662191148069907,
        0.0,
        0.14940595275487567,
        0.19358194735640444,
        2.0,
        0.0,
        0.0,
        0.0,
        0.0,
        6.0,
        0.0,
        0.0,
        0.0,
        0.0,
        0.668560701205132,
        0.0,
        0.0,
        0.0,
        0.0,
        0.0,
        0.0,
        0.0,
        0.477604568261899,
        0.0,
        0.0,
        0.0,
        0.0,
        0.0,
        0.0,
        0.0,
        0.0,
        0.0,
        0.0,
        0.0,
        0.0,
        0.0,
        0.0,
        0.0,
        0.0,
        0.0,
        0.0,
        0.0,
        0.383585445404818,
        0.0,
        0.0,
        0.0,
        0.0,
        0.0,
        0.0,
        0.0,
        0.0,
        0.0,
        0.0,
        0.0,
        0.0,
        0.041896082740418006,
        0.0,
        0.0747677257093412,
        3.764892761072587,
        0.0,
        0.0
    ],
    "x_il_mccormick": [
        0.0,
        0.3986971567243798,
        0.0,
        2.0300580678620697,
        2.4945912603897846,
        1.3170465971576317,
        0.0,
        0.0,
        0.0,
        0.9220107639685777,
        0.0,
        3.0,
        0.0,
        0.0,
        3.0,
        0.0,
        0.0,
        0.0,
        7.7011880944902495,
        0.0,
        0.0,
        0.0,
        3.0,
        0.7872895178068716,
        2.2127104821931285,
        0.0,
        0.29881190550975056,
        0.0,
        2.8033780885193007,
        0.0,
        2.6570120998887288,
        0.0,
        0.0,
        0.0,
        0.0,
        0.0,
        0.0,
        0.0,
        1.0069628317063963,
        0.0,
        0.0,
        0.0,
        3.0,
        0.0,
        0.0,
        2.136635534263392,
        0.0,
        2.937155875889373,
        0.0,
        0.0,
        0.0,
        0.0,
        0.0,
        0.0,
        5.176367567502526,
        0.0,
        0.0,
        2.92028463663219,
        0.0,
        0.0,
        0.0,
        0.0,
        0.0,
        0.06284412411062679,
        0.0,
        0.0,
        0.0,
        2.7872895178068715,
        1.3311539126707823,
        0.0,
        7.042667152916122
    ],
    "x_lj_mccormick": [
        2.0,
        4.042667152916122,
        0.0,
        1.0,
        0.7157437538820114,
        1.0,
        0.0,
        0.0,
        2.0,
        0.616414554595182,
        0.33565427723546537,
        1.196621911480699,
        0.9252322742906588,
        0.8781458142286472,
        2.0,
        0.0,
        0.0,
        0.0,
        0.8033780885193009,
        0.0,
        0.0,
        2.0,
        0.9239250520702633,
        0.0,
        0.0,
        0.0,
        5.850594047245124,
        2.1494059527548757,
        0.0,
        0.0,
        1.958103917259582,
        0.8064180526435956,
        0.23547803009682244,
        2.0,
        5.515075344073543,
        0.4849246559264565,
        2.0,
        1.0,
        0.0,
        0.0,
        1.522395431738101,
        3.653972135764425,
        0.0,
        0.6668427768375264,
        5.0,
        1.0791870328552309,
        2.0,
        0.0,
        0.0,
        1.0,
        1.6643457227645346,
        1.9996292088305907,
        0.0
    ],
    "q_mccormick": [
        0.0,
        0.3986971567243798,
        0.0,
        0.6766860226206899,
        0.3334213884187632,
        0.6013028432756202,
        0.0,
        0.0,
        0.0,
        0.3233139773793101,
        0.0,
        1.0,
        0.0,
        0.0,
        0.375,
        0.0,
        0.0,
        0.0,
        0.9626485118112812,
        0.0,
        0.0,
        0.0,
        1.0,
        0.28778815524553614,
        0.27658881027414106,
        0.0,
        0.03735148818871882,
        0.0,
        1.0,
        1.0,
        0.8321728613822673,
        0.0,
        0.0,
        0.0,
        0.0,
        0.0,
        0.0,
        0.0,
        0.16782713861773269,
        0.0,
        0.0,
        0.0,
        1.0,
        0.0,
        0.0,
        0.7122118447544639,
        0.0,
        0.979051958629791,
        0.0,
        0.0,
        0.0,
        0.0,
        0.0,
        0.0,
        1.0,
        0.0,
        0.0,
        0.48671410610536503,
        0.0,
        0.0,
        0.0,
        0.0,
        0.0,
        0.02094804137020893,
        0.0,
        0.0,
        0.0,
        0.348411189725859,
        0.17986450547587182,
        0.0,
        1.0
    ],
    "w_mccormick": [
        1.6643457227645346,
        0.9926663771241941,
        0.0,
        0.0,
        1.0069628317063963,
        0.0,
        0.0,
        0.0,
        0.0,
        0.0,
        0.0,
        0.0,
        0.0,
        0.0,
        0.0,
        0.0,
        2.0,
        0.0,
        0.0,
        1.0,
        0.0,
        0.0,
        0.0,
        0.0,
        0.0,
        0.0,
        0.0,
        0.0,
        0.6668427768375264,
        1.8277484835522584,
        0.0,
        0.0,
        0.0,
        0.0,
        0.0,
        2.92028463663219,
        0.0,
        0.0,
        0.0,
        0.0,
        0.0,
        0.25196687981555144,
        1.0791870328552309,
        0.0,
        0.0,
        0.0,
        0.0,
        0.0,
        0.0,
        1.522395431738101,
        3.653972135764425,
        0.0,
        0.0,
        0.0,
        0.0,
        0.0,
        0.0,
        0.0,
        0.0,
        2.0,
        1.0,
        0.0,
        0.0,
        0.0,
        0.0,
        0.0,
        0.0,
        0.0,
        0.0,
        0.0,
        0.0,
        0.0,
        0.0,
        0.0,
        0.75,
        2.25,
        0.0,
        0.5531776205482821,
        1.1746082057183898,
        0.4849246559264565,
        0.0,
        0.0,
        0.0,
        0.0,
        0.0,
        0.0,
        0.0,
        0.0,
        0.0,
        0.0,
        0.0,
        0.0,
        0.6968223794517179,
        2.090467138355154,
        0.0,
        0.0,
        0.0,
        0.0,
        0.0,
        0.0,
        0.0,
        1.958103917259582,
        0.8064180526435956,
        0.17263390598619566,
        0.0,
        0.0,
        0.06284412411062679,
        0.0,
        0.0,
        0.0,
        0.0,
        0.0,
        0.0,
        0.0,
        0.0,
        0.0,
        0.0,
        0.0,
        5.7758910708676865,
        1.9252970236225628,
        0.0,
        0.0,
        0.0,
        0.07470297637743764,
        0.22410892913231292,
        0.0,
        0.0,
        0.0,
        0.0,
        0.0,
        0.0,
        0.0,
        0.0,
        0.0,
        0.0,
        0.0,
        0.0,
        0.0,
        0.0,
        0.0,
        0.0,
        0.0,
        0.0,
        0.0,
        0.0,
        0.0,
        0.0,
        0.0,
        0.0,
        0.0,
        0.0,
        0.0,
        0.0,
        0.5755763104910723,
        0.2117132073157994,
        0.0,
        0.0,
        1.4244236895089277,
        0.7122118447544639,
        0.0,
        0.0,
        0.0,
        0.0,
        0.0,
        0.0,
        0.0,
        0.0,
        0.0,
        0.0,
        0.0,
        0.0,
        0.0,
        0.0,
        2.0,
        0.0,
        0.0,
        0.0,
        0.8033780885193009,
        0.0,
        0.0,
        0.0,
        0.0,
        0.0,
        0.0,
        0.0,
        0.0,
        0.0,
        0.0,
        0.0,
        0.0,
        0.0,
        0.0,
        0.0,
        0.0,
        1.1966219114806989,
        0.9252322742906588,
        0.8781458142286472,
        0.0,
        0.0,
        0.0,
        0.0,
        0.0,
        0.0,
        0.0,
        0.0,
        0.0,
        1.3533720452413798,
        0.3410317453852245,
        0.33565427723546537,
        0.6466279547586202,
        0.2753828092099575,
        0.0,
        0.0,
        0.0,
        0.0,
        0.0,
        0.0,
        0.0,
        0.0,
        0.0,
        0.0,
        0.0,
        0.3986971567243798,
        0.0,
        0.0,
        0.7157437538820114,
        0.6013028432756202,
        0.0,
        0.0,
        0.0,
        0.0,
        0.0,
        0.0,
        0.0,
        0.0,
        0.0,
        0.0,
        0.0,
        0.0,
        0.0,
        0.0,
        0.0,
        0.0,
        0.0,
        0.0,
        0.0,
        0.0,
        0.0,
        0.0,
        0.0,
        0.0,
        0.0,
        0.0,
        0.0,
        0.0,
        0.0,
        0.0,
        2.0,
        4.042667152916122,
        0.0,
        1.0
    ]
}