{
    "x_ij_mccormick": [
        0.0,
        0.0,
        0.0,
        0.0,
        0.002456994052030703,
        0.0,
        1.2971482991548493,
        0.0,
        0.0,
        0.0,
        0.0,
        0.0,
        0.0,
        0.0,
        0.0,
        0.0,
        0.0,
        0.0,
        0.2754688794596779,
        0.0,
        0.2679777161893213,
        0.0,
        0.0,
        0.0,
        0.0,
        0.0,
        0.0,
        2.0,
        0.0,
        0.0,
        0.0,
        0.0,
        0.0,
        0.0,
        0.0,
        0.0,
        0.0,
        0.0,
        0.0,
        0.0,
        0.0,
        0.0,
        0.0,
        0.0,
        0.7885723549429242,
        0.0,
        0.0,
        0.0,
        0.0,
        0.0,
        0.0,
        0.0,
        0.0,
        0.0,
        0.0,
        0.22932083666489778,
        0.0,
        0.0,
        0.050668320306776767,
        1.8627238325341675,
        0.0,
        0.0,
        0.0,
        0.0,
        6.0,
        0.0,
        0.0,
        0.0,
        0.0,
        0.7245311205403221,
        0.0,
        0.0,
        0.0,
        0.0,
        0.0,
        0.0,
        0.0,
        0.8824862916569423,
        0.0,
        0.0,
        0.0,
        0.0,
        0.0,
        0.0,
        0.0,
        0.0,
        0.0,
        0.0,
        0.0,
        0.0,
        0.0,
        0.0,
        0.0,
        0.0,
        0.0,
        0.0,
        0.0,
        0.7188084139366708,
        0.0,
        0.0,
        0.0,
        0.0,
        0.0,
        0.0,
        0.0,
        0.0,
        0.0,
        0.0,
        0.0,
        0.0,
        0.0,
        0.0,
        0.05465355477855464,
        2.267635655841937,
        0.0,
        0.0
    ],
    "x_il_mccormick": [
        0.0,
        0.0,
        0.0,
        2.1494845577213844,
        4.416195060475992,
        1.3697634298070007,
        0.0,
        0.0,
        0.0,
        0.7478036853341303,
        0.0,
        3.0,
        0.0,
        0.0,
        2.934104420212998,
        0.0,
        0.0,
        0.0,
        8.0,
        0.0,
        1.2959380994514906,
        0.33308827103815003,
        3.0,
        1.0883938399846955,
        1.9116061600153045,
        0.0,
        0.0,
        0.0,
        2.7706791633351022,
        0.0,
        2.9493316796932234,
        0.0,
        0.0,
        0.0,
        0.0,
        0.0,
        0.0,
        0.0,
        1.8482899709765561,
        0.21101814252593248,
        0.0,
        0.0,
        3.0,
        0.0,
        0.0,
        1.8089659706308614,
        0.0,
        3.0,
        0.0,
        0.0,
        0.0,
        0.0,
        0.0,
        0.0,
        3.6693307026120516,
        0.0,
        0.0,
        0.0,
        0.0,
        0.0,
        0.0,
        0.0,
        0.0,
        0.0,
        0.13727616746583243,
        0.0,
        0.0,
        3.1542894197716973,
        2.5234213696078105,
        0.0,
        7.15592742989627
    ],
    "x_lj_mccormick": [
        1.9975430059479693,
        4.4749116377372,
        0.0,
        0.8944909287370337,
        0.7028517008451507,
        1.0,
        0.0,
        0.0,
        2.0,
        0.2811915860633292,
        0.6160966569921855,
        1.2293208366648976,
        0.9453464452214454,
        0.825332718113657,
        2.0,
        0.0,
        0.0,
        0.0,
        0.7706791633351024,
        0.0,
        0.0,
        2.0,
        0.897359810615557,
        0.13727616746583243,
        0.0,
        0.0,
        6.0,
        2.0,
        0.0,
        0.0,
        2.0,
        0.9493316796932232,
        0.050668320306776815,
        2.0,
        5.211427645057076,
        0.7885723549429243,
        2.0,
        1.0,
        0.0,
        0.0,
        1.1175137083430577,
        3.7706791633351022,
        0.07707593038538252,
        1.2114276450570758,
        5.028433140877583,
        0.6997556441491437,
        1.9229240696146175,
        0.10550907126296627,
        0.0,
        0.9715668591224165,
        1.3839033430078145,
        3.4137183076619646,
        0.0
    ],
    "q_mccormick": [
        0.0,
        0.0,
        0.0,
        0.716494852573795,
        0.6057138225285379,
        0.66691172896185,
        0.0,
        0.0,
        0.0,
        0.28350514742620503,
        0.0,
        0.9999999999999999,
        0.0,
        0.0,
        0.36676305252662483,
        0.0,
        0.0,
        0.0,
        1.0,
        0.0,
        0.44124314582847113,
        0.33308827103815003,
        1.0,
        0.39701134312304615,
        0.23895077000191306,
        0.0,
        0.0,
        0.0,
        1.0,
        0.0,
        0.6919516715039072,
        0.0,
        0.0,
        0.0,
        0.0,
        0.0,
        0.0,
        0.0,
        0.30804832849609276,
        0.10550907126296624,
        0.0,
        0.0,
        1.0,
        0.0,
        0.0,
        0.6029886568769538,
        0.0,
        1.0,
        0.0,
        0.0,
        0.0,
        0.0,
        0.0,
        0.0,
        0.5587568541715289,
        0.0,
        0.0,
        0.0,
        0.0,
        0.0,
        0.0,
        0.0,
        0.0,
        0.0,
        1.0,
        0.0,
        0.0,
        0.39428617747146216,
        0.3942861774714621,
        0.0,
        0.8944909287370337
    ],
    "w_mccormick": [
        1.3839033430078145,
        1.5654283366854087,
        0.0,
        0.0,
        1.8482899709765561,
        0.0,
        0.0,
        0.0,
        0.0,
        0.0,
        0.0,
        0.0,
        0.0,
        0.0,
        0.0,
        0.0,
        1.9229240696146175,
        0.10550907126296605,
        0.0,
        0.9715668591224165,
        0.0,
        0.0,
        0.0,
        0.0,
        0.0,
        0.0,
        0.0,
        0.0,
        1.2114276450570758,
        3.2047674154189165,
        0.0,
        0.0,
        0.0,
        0.0,
        0.0,
        0.0,
        0.0,
        0.0,
        0.0,
        0.0,
        0.0,
        1.8236657254586663,
        0.6997556441491438,
        0.0,
        1.2959380994514906,
        0.0,
        0.0,
        0.0,
        0.0,
        1.1175137083430577,
        2.4747410638836116,
        0.07707593038538252,
        0.0,
        0.0,
        0.0,
        0.0,
        0.0,
        0.0,
        0.0,
        2.0,
        1.0,
        0.0,
        0.0,
        0.0,
        0.0,
        0.0,
        0.0,
        0.0,
        0.0,
        0.0,
        0.0,
        0.0,
        0.0,
        0.0,
        0.7335261050532497,
        2.2005783151597487,
        0.0,
        0.4779015400038261,
        1.4337046200114782,
        0.0,
        0.0,
        0.0,
        0.0,
        0.0,
        0.0,
        0.0,
        0.0,
        0.0,
        0.0,
        0.0,
        0.0,
        0.0,
        0.7885723549429243,
        1.5771447098858489,
        0.7885723549429243,
        0.0,
        0.0,
        0.0,
        0.0,
        0.0,
        0.0,
        2.0,
        0.9493316796932232,
        0.050668320306776815,
        0.0,
        0.0,
        0.0,
        0.0,
        0.0,
        0.0,
        0.0,
        0.0,
        0.0,
        0.0,
        0.0,
        0.0,
        0.0,
        0.0,
        6.0,
        2.0,
        0.0,
        0.0,
        0.0,
        0.0,
        0.0,
        0.0,
        0.0,
        0.0,
        0.0,
        0.0,
        0.0,
        0.0,
        0.0,
        0.0,
        0.0,
        0.0,
        0.0,
        0.0,
        0.0,
        0.0,
        0.0,
        0.0,
        0.0,
        0.0,
        0.0,
        0.0,
        0.0,
        0.0,
        0.0,
        0.0,
        0.0,
        0.13727616746583243,
        0.0,
        0.7940226862460923,
        0.29437115373860323,
        0.0,
        0.0,
        1.2059773137539076,
        0.6029886568769538,
        0.0,
        0.0,
        0.0,
        0.0,
        0.0,
        0.0,
        0.0,
        0.0,
        0.0,
        0.0,
        0.0,
        0.0,
        0.0,
        0.0,
        2.0,
        0.0,
        0.0,
        0.0,
        0.7706791633351024,
        0.0,
        0.0,
        0.0,
        0.0,
        0.0,
        0.0,
        0.0,
        0.0,
        0.0,
        0.0,
        0.0,
        0.0,
        0.0,
        0.0,
        0.0,
        0.0,
        1.2293208366648976,
        0.9453464452214454,
        0.825332718113657,
        0.0,
        0.0,
        0.0,
        0.0,
        0.0,
        0.0,
        0.0,
        0.0,
        0.0,
        1.43298970514759,
        0.1003981955816089,
        0.6160966569921855,
        0.5670102948524101,
        0.18079339048172033,
        0.0,
        0.0,
        0.0,
        0.0,
        0.0,
        0.0,
        0.0,
        0.0,
        0.0,
        0.0,
        0.0,
        0.0,
        0.0,
        0.0,
        0.7028517008451507,
        0.66691172896185,
        0.0,
        0.0,
        0.0,
        0.0,
        0.0,
        0.0,
        0.0,
        0.33308827103815003,
        0.0,
        0.0,
        0.0,
        0.0,
        0.0,
        0.0,
        0.0,
        0.0,
        0.0,
        0.0,
        0.0,
        0.0,
        0.0,
        0.0,
        0.21101814252593248,
        0.0,
        0.0,
        0.0,
        0.0,
        0.0,
        0.0,
        0.0,
        1.7865248634220368,
        4.4749116377372,
        0.0,
        0.8944909287370337
    ]
}