{
    "upper_bound_presolve": -631.8525643991644,
    "x_ij_presolve": [
        0.0,
        0.3948623296915689,
        1.1573674889959311,
        0.0,
        0.0,
        0.0,
        1.6860939330748863,
        0.0,
        0.0,
        0.0,
        0.0,
        0.0,
        0.0,
        0.0,
        0.0,
        0.0,
        0.0,
        0.0,
        0.25374770264668967,
        0.0,
        0.001354567864896445,
        0.0,
        0.0,
        0.0,
        0.0,
        0.0,
        0.0,
        2.0,
        0.0,
        0.0,
        0.0,
        0.0,
        0.0,
        0.0,
        0.0,
        0.0,
        0.0,
        0.0,
        0.0,
        0.0,
        0.0,
        0.0,
        0.0,
        0.8426325110040692,
        0.0,
        0.0,
        0.0,
        0.0,
        0.0,
        0.0,
        0.0,
        0.0,
        0.0,
        0.0,
        0.0,
        0.998992971402998,
        0.0,
        1.0362028095389766,
        0.1357017112301034,
        1.7692668519043941,
        0.0,
        0.0,
        0.0,
        0.0,
        6.0,
        0.0,
        0.0,
        0.0,
        0.0,
        0.7462522973533103,
        0.0,
        0.0,
        0.0,
        0.0,
        0.0,
        0.0,
        0.08830805209547515,
        0.9073006791796795,
        0.0,
        0.0,
        0.0,
        0.0,
        0.0,
        0.0,
        0.0,
        0.0,
        0.0,
        0.0,
        0.0,
        0.0,
        0.0,
        1.0926993208203206,
        0.0,
        0.0,
        0.0,
        0.0,
        0.0,
        0.0,
        0.0,
        0.0,
        0.0,
        0.0,
        0.0,
        0.0,
        0.0,
        0.0,
        0.0,
        0.0,
        0.03482482635219574,
        0.0,
        0.0,
        0.0,
        0.0,
        5.859481549355298,
        0.0,
        0.0
    ],
    "x_il_presolve": [
        0.0,
        0.0,
        0.0,
        2.2608996525643135,
        1.6543164120666118,
        1.2255980148296386,
        0.0,
        0.0,
        1.0454315042959241,
        0.7391003474356863,
        0.0,
        3.0,
        0.0,
        0.0,
        3.0,
        0.0,
        0.0,
        0.0,
        7.157367488995931,
        0.0,
        0.0,
        0.0,
        3.0,
        1.185949954940627,
        1.8140500450593733,
        0.0,
        0.8426325110040692,
        0.0,
        2.001007028597002,
        0.0,
        1.8280954792309199,
        0.0,
        0.0,
        0.0,
        0.0,
        0.0,
        0.0,
        0.0,
        0.3110684035488861,
        0.32545526283444487,
        0.0,
        0.0,
        3.0,
        0.0,
        0.0,
        1.8140500450593733,
        0.0,
        2.8642982887698967,
        0.0,
        0.0,
        0.0,
        0.0,
        0.0,
        0.0,
        0.0,
        0.0,
        0.0,
        6.3456835879333875,
        0.0,
        0.0,
        0.0,
        0.0,
        0.0,
        0.0,
        0.23073314809560583,
        0.0,
        0.0,
        2.140518450644702,
        0.0,
        0.0,
        5.24385055252479
    ],
    "x_lj_presolve": [
        2.0,
        2.5693058153592343,
        0.0,
        1.0,
        0.31390606692511364,
        0.9116919479045249,
        0.0,
        0.0,
        2.0,
        1.0,
        0.0,
        1.6041306417114292,
        1.0,
        0.39586935828857056,
        1.605137670308431,
        0.0,
        0.0,
        0.0,
        0.39586935828857095,
        0.0,
        0.0,
        2.0,
        1.0,
        0.23073314809560583,
        0.0,
        0.0,
        4.963797190461023,
        3.0362028095389766,
        0.0,
        0.0,
        2.0,
        0.8642982887698967,
        0.0,
        2.0,
        6.0,
        0.0,
        2.0,
        1.0,
        0.0,
        0.0,
        0.0,
        0.0,
        0.0,
        0.0,
        4.965175173647805,
        3.034824826352195,
        1.9651751736478045,
        0.0,
        0.0,
        1.0348248263521955,
        2.0,
        0.13916388277980615,
        0.0
    ],
    "q_presolve": [
        0.0,
        0.0,
        0.0,
        0.7536332175214379,
        0.20678955150832648,
        1.0,
        0.0,
        0.0,
        0.13067893803699052,
        0.2463667824785621,
        0.0,
        1.0,
        0.0,
        0.0,
        0.375,
        0.0,
        0.0,
        0.0,
        0.8946709361244913,
        0.0,
        0.0,
        0.0,
        1.0,
        0.3953166516468756,
        0.22675625563242166,
        0.0,
        0.10532906387550865,
        0.0,
        1.0,
        0.0,
        0.8545841176298011,
        0.0,
        0.0,
        0.0,
        0.0,
        0.0,
        0.0,
        0.0,
        0.14541588237019884,
        0.05843731222963058,
        0.0,
        0.0,
        1.0,
        0.0,
        0.0,
        0.6046833483531244,
        0.0,
        1.0,
        0.0,
        0.0,
        0.0,
        0.0,
        0.0,
        0.0,
        0.0,
        1.0,
        0.0,
        0.7932104484916734,
        0.0,
        0.0,
        0.0,
        0.0,
        0.0,
        0.0,
        1.0,
        0.0,
        0.0,
        0.26756480633058777,
        0.0,
        0.0,
        0.9415626877703694
    ],
    "w_presolve": [
        1.7091682352596023,
        0.11892724397131771,
        0.0,
        0.2908317647403977,
        0.02023663880848843,
        0.0,
        0.0,
        0.0,
        0.0,
        0.0,
        0.0,
        0.0,
        0.0,
        0.0,
        0.0,
        0.0,
        1.9651751736478045,
        0.0,
        0.0,
        1.0348248263521955,
        0.0,
        0.0,
        0.0,
        0.0,
        0.0,
        0.0,
        0.0,
        0.0,
        0.0,
        1.0267463473189067,
        0.6275700647477052,
        0.0,
        0.0,
        0.0,
        0.0,
        3.9384288263288973,
        2.4072547616044897,
        0.0,
        0.0,
        0.0,
        0.0,
        0.0,
        0.0,
        0.0,
        0.0,
        0.0,
        0.0,
        0.0,
        0.0,
        0.0,
        0.0,
        0.0,
        0.0,
        0.0,
        0.0,
        0.0,
        0.0,
        0.0,
        0.0,
        2.0,
        1.0,
        0.0,
        0.0,
        0.0,
        0.0,
        0.0,
        0.0,
        0.0,
        0.0,
        0.0,
        0.0,
        0.26135787607398114,
        0.7840736282219432,
        0.0,
        0.75,
        2.25,
        0.0,
        0.4535125112648433,
        1.36053753379453,
        0.0,
        0.0,
        0.0,
        0.0,
        0.0,
        0.0,
        0.0,
        0.0,
        0.0,
        0.0,
        0.0,
        0.0,
        0.0,
        0.5351296126611755,
        1.6053888379835266,
        0.0,
        0.0,
        0.0,
        0.0,
        0.0,
        0.0,
        0.0,
        2.0,
        0.8642982887698967,
        0.0,
        0.0,
        0.0,
        0.0,
        0.0,
        0.0,
        0.0,
        0.0,
        0.0,
        0.0,
        0.0,
        0.0,
        0.0,
        0.0,
        0.0,
        4.440965079121884,
        2.7164024098740467,
        0.0,
        0.0,
        0.0,
        0.5228321113391395,
        0.3198003996649297,
        0.0,
        0.0,
        0.0,
        0.0,
        0.0,
        0.0,
        0.0,
        0.0,
        0.0,
        0.0,
        0.0,
        0.0,
        0.0,
        0.0,
        0.0,
        0.0,
        0.0,
        0.0,
        0.0,
        0.0,
        0.0,
        0.0,
        0.0,
        0.0,
        0.0,
        0.0,
        0.23073314809560583,
        0.0,
        0.7906333032937513,
        0.3953166516468756,
        0.0,
        0.0,
        1.2093666967062489,
        0.6046833483531244,
        0.0,
        0.0,
        0.0,
        0.0,
        0.0,
        0.0,
        0.0,
        0.0,
        0.0,
        0.0,
        0.0,
        0.0,
        0.0,
        0.0,
        1.605137670308431,
        0.0,
        0.0,
        0.0,
        0.39586935828857095,
        0.0,
        0.0,
        0.0,
        0.0,
        0.0,
        0.0,
        0.0,
        0.0,
        0.0,
        0.0,
        0.0,
        0.0,
        0.0,
        0.0,
        0.0,
        0.0,
        1.6041306417114292,
        1.0,
        0.3958693582885706,
        0.0,
        0.0,
        0.0,
        0.0,
        0.0,
        0.0,
        0.0,
        0.0,
        0.0,
        1.5072664350428757,
        0.7536332175214377,
        0.0,
        0.4927335649571242,
        0.24636678247856206,
        0.0,
        0.0,
        0.0,
        0.0,
        0.0,
        0.0,
        0.0,
        0.0,
        0.0,
        0.0,
        0.0,
        0.0,
        0.0,
        0.0,
        0.31390606692511364,
        0.9116919479045249,
        0.0,
        0.0,
        0.0,
        0.0,
        0.0,
        0.0,
        0.0,
        0.0,
        0.0,
        0.0,
        0.0,
        0.0,
        0.0,
        0.0,
        0.0,
        0.0,
        0.0,
        0.0,
        0.0,
        0.0,
        0.0,
        0.0,
        0.11687462445926115,
        0.15014332614555315,
        0.0,
        0.05843731222963056,
        0.0,
        0.0,
        0.0,
        0.0,
        1.8831253755407389,
        2.419162489213681,
        0.0,
        0.9415626877703694
    ]
}